[
  {
    "codigoBarra": "020811309002",
    "idc": 5,
    "name": "8113",
    "talle": 90,
    "color": "NEGRO",
    "unit_price": 11073.3,
    "stock": 0,
    "visible": "true",
    "category": "kaury"
  },
  {
    "codigoBarra": "020811310002",
    "idc": 6,
    "name": "8113",
    "talle": 100,
    "color": "NEGRO",
    "unit_price": 11073.3,
    "stock": 6,
    "visible": "true",
    "category": "kaury"
  },
  {
    "codigoBarra": "020811310502",
    "idc": 7,
    "name": "8113",
    "talle": 105,
    "color": "NEGRO",
    "unit_price": 11073.3,
    "stock": -1,
    "visible": "true",
    "category": "kaury"
  },
  {
    "codigoBarra": "02807009558",
    "idc": 8,
    "name": "8070",
    "talle": 95,
    "color": "BORDO",
    "unit_price": 9345.01,
    "stock": -1,
    "visible": "true",
    "category": "kaury"
  },
  {
    "codigoBarra": "02807010058",
    "idc": 9,
    "name": "8070",
    "talle": 100,
    "color": "BORDO",
    "unit_price": 9345.01,
    "stock": 2,
    "visible": "true",
    "category": "kaury"
  },
  {
    "codigoBarra": "020811309502",
    "idc": 10,
    "name": "8113",
    "talle": 95,
    "color": "NEGRO",
    "unit_price": 11073.3,
    "stock": 0,
    "visible": "true",
    "category": "kaury"
  },
  {
    "codigoBarra": "020813009590",
    "idc": 12,
    "name": "8130",
    "talle": 95,
    "color": "ROSA VINTAGE",
    "unit_price": 9588.59,
    "stock": 5,
    "visible": "true",
    "category": "kaury"
  },
  {
    "codigoBarra": "020813009090",
    "idc": 13,
    "name": "8130",
    "talle": 90,
    "color": "ROSA VINTAGE",
    "unit_price": 9588.59,
    "stock": 5,
    "visible": "true",
    "category": "kaury"
  },
  {
    "codigoBarra": "020813009002",
    "idc": 14,
    "name": "8130",
    "talle": 90,
    "color": "NEGRO",
    "unit_price": 9588.59,
    "stock": 2,
    "visible": "true",
    "category": "kaury"
  },
  {
    "codigoBarra": "020813009502",
    "idc": 15,
    "name": "8130",
    "talle": 95,
    "color": "NEGRO",
    "unit_price": 9588.59,
    "stock": 1,
    "visible": "true",
    "category": "kaury"
  },
  {
    "codigoBarra": "020813008502",
    "idc": 16,
    "name": "8130",
    "talle": 85,
    "color": "NEGRO",
    "unit_price": 9588.59,
    "stock": 11,
    "visible": "true",
    "category": "kaury"
  },
  {
    "codigoBarra": "020813009001",
    "idc": 17,
    "name": "8130",
    "talle": 90,
    "color": "BLANCO",
    "unit_price": 9588.59,
    "stock": 13,
    "visible": "true",
    "category": "kaury"
  },
  {
    "codigoBarra": "020813008501",
    "idc": 18,
    "name": "8130",
    "talle": 85,
    "color": "BLANCO",
    "unit_price": 9588.59,
    "stock": 7,
    "visible": "true",
    "category": "kaury"
  },
  {
    "codigoBarra": "020813010001",
    "idc": 19,
    "name": "8130",
    "talle": 100,
    "color": "BLANCO",
    "unit_price": 9588.59,
    "stock": 3,
    "visible": "true",
    "category": "kaury"
  },
  {
    "codigoBarra": "020813009501",
    "idc": 20,
    "name": "8130",
    "talle": 95,
    "color": "BLANCO",
    "unit_price": 9588.59,
    "stock": 2,
    "visible": "true",
    "category": "kaury"
  },
  {
    "codigoBarra": "020813009073",
    "idc": 22,
    "name": "8130",
    "talle": 90,
    "color": "GRIS CLARO",
    "unit_price": 9588.59,
    "stock": 3,
    "visible": "true",
    "category": "kaury"
  },
  {
    "codigoBarra": "020813009573",
    "idc": 23,
    "name": "8130",
    "talle": 95,
    "color": "GRIS CLARO",
    "unit_price": 9588.59,
    "stock": 5,
    "visible": "true",
    "category": "kaury"
  },
  {
    "codigoBarra": "020813010073",
    "idc": 24,
    "name": "8130",
    "talle": 100,
    "color": "GRIS CLARO",
    "unit_price": 9588.59,
    "stock": 7,
    "visible": "true",
    "category": "kaury"
  },
  {
    "codigoBarra": "020403008502",
    "idc": 25,
    "name": "4030",
    "talle": 85,
    "color": "NEGRO",
    "unit_price": 13030.5,
    "stock": 5,
    "visible": "true",
    "category": "kaury"
  },
  {
    "codigoBarra": "020403009002",
    "idc": 26,
    "name": "4030",
    "talle": 90,
    "color": "NEGRO",
    "unit_price": 13030.5,
    "stock": 3,
    "visible": "true",
    "category": "kaury"
  },
  {
    "codigoBarra": "020403009502",
    "idc": 27,
    "name": "4030",
    "talle": 95,
    "color": "NEGRO",
    "unit_price": 13030.5,
    "stock": 1,
    "visible": "true",
    "category": "kaury"
  },
  {
    "codigoBarra": "020403010002",
    "idc": 28,
    "name": "4030",
    "talle": 100,
    "color": "NEGRO",
    "unit_price": 13030.5,
    "stock": 0,
    "visible": "true",
    "category": "kaury"
  },
  {
    "codigoBarra": "020403008501",
    "idc": 29,
    "name": "4030",
    "talle": 85,
    "color": "BLANCO",
    "unit_price": 13030.5,
    "stock": 0,
    "visible": "true",
    "category": "kaury"
  },
  {
    "codigoBarra": "020403009001",
    "idc": 30,
    "name": "4030",
    "talle": 90,
    "color": "BLANCO",
    "unit_price": 13030.5,
    "stock": 6,
    "visible": "true",
    "category": "kaury"
  },
  {
    "codigoBarra": "020403009501",
    "idc": 31,
    "name": "4030",
    "talle": 95,
    "color": "BLANCO",
    "unit_price": 13030.5,
    "stock": 3,
    "visible": "true",
    "category": "kaury"
  },
  {
    "codigoBarra": "020403010001",
    "idc": 32,
    "name": "4030",
    "talle": 100,
    "color": "BLANCO",
    "unit_price": 13030.5,
    "stock": 3,
    "visible": "true",
    "category": "kaury"
  },
  {
    "codigoBarra": "020403009090",
    "idc": 33,
    "name": "4030",
    "talle": 90,
    "color": "ROSA VINTAGE",
    "unit_price": 13030.5,
    "stock": 26,
    "visible": "true",
    "category": "kaury"
  },
  {
    "codigoBarra": "020403009590",
    "idc": 34,
    "name": "4030",
    "talle": 95,
    "color": "ROSA VINTAGE",
    "unit_price": 13030.5,
    "stock": 8,
    "visible": "true",
    "category": "kaury"
  },
  {
    "codigoBarra": "020403010090",
    "idc": 35,
    "name": "4030",
    "talle": 100,
    "color": "ROSA VINTAGE",
    "unit_price": 13030.5,
    "stock": 3,
    "visible": "true",
    "category": "kaury"
  },
  {
    "codigoBarra": "020403008590",
    "idc": 36,
    "name": "4030",
    "talle": 85,
    "color": "ROSA VINTAGE",
    "unit_price": 13030.5,
    "stock": -2,
    "visible": "true",
    "category": "kaury"
  },
  {
    "codigoBarra": "020403009503",
    "idc": 37,
    "name": "4030",
    "talle": 95,
    "color": "ROJO",
    "unit_price": 13030.5,
    "stock": 3,
    "visible": "true",
    "category": "kaury"
  },
  {
    "codigoBarra": "020403008503",
    "idc": 38,
    "name": "4030",
    "talle": 85,
    "color": "ROJO",
    "unit_price": 13030.5,
    "stock": 12,
    "visible": "true",
    "category": "kaury"
  },
  {
    "codigoBarra": "020403009003",
    "idc": 39,
    "name": "4030",
    "talle": 90,
    "color": "ROJO",
    "unit_price": 13030.5,
    "stock": 13,
    "visible": "true",
    "category": "kaury"
  },
  {
    "codigoBarra": "020403010003",
    "idc": 40,
    "name": "4030",
    "talle": 100,
    "color": "ROJO",
    "unit_price": 13030.5,
    "stock": 11,
    "visible": "true",
    "category": "kaury"
  },
  {
    "codigoBarra": "020403009553",
    "idc": 41,
    "name": "4030",
    "talle": 95,
    "color": "NUDE",
    "unit_price": 13030.5,
    "stock": 1,
    "visible": "true",
    "category": "kaury"
  },
  {
    "codigoBarra": "020403008553",
    "idc": 42,
    "name": "4030",
    "talle": 85,
    "color": "NUDE",
    "unit_price": 13030.5,
    "stock": 6,
    "visible": "true",
    "category": "kaury"
  },
  {
    "codigoBarra": "020403010053",
    "idc": 43,
    "name": "4030",
    "talle": 100,
    "color": "NUDE",
    "unit_price": 13030.5,
    "stock": 2,
    "visible": "true",
    "category": "kaury"
  },
  {
    "codigoBarra": "020403009053",
    "idc": 44,
    "name": "4030",
    "talle": 90,
    "color": "NUDE",
    "unit_price": 13030.5,
    "stock": 5,
    "visible": "true",
    "category": "kaury"
  },
  {
    "codigoBarra": "020403009578",
    "idc": 45,
    "name": "4030",
    "talle": 95,
    "color": "VERDE MILITAR",
    "unit_price": 13030.5,
    "stock": 15,
    "visible": "true",
    "category": "kaury"
  },
  {
    "codigoBarra": "020403010078",
    "idc": 46,
    "name": "4030",
    "talle": 100,
    "color": "VERDE MILITAR",
    "unit_price": 13030.5,
    "stock": 2,
    "visible": "true",
    "category": "kaury"
  },
  {
    "codigoBarra": "020403008578",
    "idc": 47,
    "name": "4030",
    "talle": 85,
    "color": "VERDE MILITAR",
    "unit_price": 13030.5,
    "stock": 9,
    "visible": "true",
    "category": "kaury"
  },
  {
    "codigoBarra": "020403009078",
    "idc": 48,
    "name": "4030",
    "talle": 90,
    "color": "VERDE MILITAR",
    "unit_price": 13030.5,
    "stock": 15,
    "visible": "true",
    "category": "kaury"
  },
  {
    "codigoBarra": "020479009501",
    "idc": 49,
    "name": "4790",
    "talle": 95,
    "color": "BLANCO",
    "unit_price": 12721.8,
    "stock": 3,
    "visible": "true",
    "category": "kaury"
  },
  {
    "codigoBarra": "020479009090",
    "idc": 50,
    "name": "4790",
    "talle": 90,
    "color": "ROSA VINTAGE",
    "unit_price": 12721.8,
    "stock": 3,
    "visible": "true",
    "category": "kaury"
  },
  {
    "codigoBarra": "020479008503",
    "idc": 51,
    "name": "4790",
    "talle": 85,
    "color": "ROJO",
    "unit_price": 12721.8,
    "stock": 3,
    "visible": "true",
    "category": "kaury"
  },
  {
    "codigoBarra": "020479010078",
    "idc": 52,
    "name": "4790",
    "talle": 100,
    "color": "VERDE MILITAR",
    "unit_price": 12721.8,
    "stock": 2,
    "visible": "true",
    "category": "kaury"
  },
  {
    "codigoBarra": "020809509590",
    "idc": 53,
    "name": "8095",
    "talle": 95,
    "color": "ROSA VINTAGE",
    "unit_price": 8101.8,
    "stock": 0,
    "visible": "true",
    "category": "kaury"
  },
  {
    "codigoBarra": "020809510590",
    "idc": 54,
    "name": "8095",
    "talle": 105,
    "color": "ROSA VINTAGE",
    "unit_price": 8101.8,
    "stock": 3,
    "visible": "true",
    "category": "kaury"
  },
  {
    "codigoBarra": "020809509090",
    "idc": 55,
    "name": "8095",
    "talle": 90,
    "color": "ROSA VINTAGE",
    "unit_price": 8101.8,
    "stock": 3,
    "visible": "true",
    "category": "kaury"
  },
  {
    "codigoBarra": "020809009002",
    "idc": 56,
    "name": "8090",
    "talle": 90,
    "color": "NEGRO",
    "unit_price": 10248.01,
    "stock": 5,
    "visible": "true",
    "category": "kaury"
  },
  {
    "codigoBarra": "020809009502",
    "idc": 57,
    "name": "8090",
    "talle": 95,
    "color": "NEGRO",
    "unit_price": 10248.01,
    "stock": 0,
    "visible": "true",
    "category": "kaury"
  },
  {
    "codigoBarra": "020809010503",
    "idc": 58,
    "name": "8090",
    "talle": 105,
    "color": "ROJO",
    "unit_price": 10248.01,
    "stock": 3,
    "visible": "true",
    "category": "kaury"
  },
  {
    "codigoBarra": "02707009578",
    "idc": 59,
    "name": "7070",
    "talle": 95,
    "color": "VERDE C/NUDE",
    "unit_price": 12396.29,
    "stock": 0,
    "visible": "true",
    "category": "kaury"
  },
  {
    "codigoBarra": "02707010078",
    "idc": 60,
    "name": "7070",
    "talle": 100,
    "color": "VERDE C/NUDE",
    "unit_price": 12396.29,
    "stock": 23,
    "visible": "true",
    "category": "kaury"
  },
  {
    "codigoBarra": "02702009078",
    "idc": 61,
    "name": "7020",
    "talle": 90,
    "color": "VERDE MILITAR",
    "unit_price": 9806.99,
    "stock": 26,
    "visible": "true",
    "category": "kaury"
  },
  {
    "codigoBarra": "02702009090",
    "idc": 62,
    "name": "7020",
    "talle": 90,
    "color": "ROSA VINTAGE",
    "unit_price": 9806.99,
    "stock": 0,
    "visible": "true",
    "category": "kaury"
  },
  {
    "codigoBarra": "02702009558",
    "idc": 63,
    "name": "7020",
    "talle": 95,
    "color": "BORDO",
    "unit_price": 9806.99,
    "stock": 2,
    "visible": "true",
    "category": "kaury"
  },
  {
    "codigoBarra": "02702009058",
    "idc": 64,
    "name": "7020",
    "talle": 90,
    "color": "BORDO",
    "unit_price": 9806.99,
    "stock": 2,
    "visible": "true",
    "category": "kaury"
  },
  {
    "codigoBarra": "02702010058",
    "idc": 65,
    "name": "7020",
    "talle": 100,
    "color": "BORDO",
    "unit_price": 9806.99,
    "stock": 5,
    "visible": "true",
    "category": "kaury"
  },
  {
    "codigoBarra": "02702009002",
    "idc": 66,
    "name": "7020",
    "talle": 90,
    "color": "NEGRO",
    "unit_price": 9806.99,
    "stock": 1,
    "visible": "true",
    "category": "kaury"
  },
  {
    "codigoBarra": "02702010002",
    "idc": 67,
    "name": "7020",
    "talle": 100,
    "color": "NEGRO",
    "unit_price": 9806.99,
    "stock": 7,
    "visible": "true",
    "category": "kaury"
  },
  {
    "codigoBarra": "02702009502",
    "idc": 68,
    "name": "7020",
    "talle": 95,
    "color": "NEGRO",
    "unit_price": 9806.99,
    "stock": 4,
    "visible": "true",
    "category": "kaury"
  },
  {
    "codigoBarra": "020816508558",
    "idc": 70,
    "name": "8165",
    "talle": 85,
    "color": "BORDO",
    "unit_price": 11407.21,
    "stock": 0,
    "visible": "true",
    "category": "kaury"
  },
  {
    "codigoBarra": "020816509058",
    "idc": 71,
    "name": "8165",
    "talle": 90,
    "color": "BORDO",
    "unit_price": 11407.21,
    "stock": 1,
    "visible": "true",
    "category": "kaury"
  },
  {
    "codigoBarra": "0110100109032",
    "idc": 76,
    "name": "1001",
    "talle": 90,
    "color": "VERDE MILITAR",
    "unit_price": 6354.61,
    "stock": 1,
    "visible": "true",
    "category": "kaury"
  },
  {
    "codigoBarra": "0110100109001",
    "idc": 78,
    "name": "1001",
    "talle": 90,
    "color": "NEGRO",
    "unit_price": 6354.61,
    "stock": 3,
    "visible": "true",
    "category": "kaury"
  },
  {
    "codigoBarra": "0110100109501",
    "idc": 79,
    "name": "1001",
    "talle": 95,
    "color": "NEGRO",
    "unit_price": 6354.61,
    "stock": 2,
    "visible": "true",
    "category": "kaury"
  },
  {
    "codigoBarra": "0110100110001",
    "idc": 80,
    "name": "1001",
    "talle": 100,
    "color": "NEGRO",
    "unit_price": 6354.61,
    "stock": 0,
    "visible": "true",
    "category": "kaury"
  },
  {
    "codigoBarra": "0110100110002",
    "idc": 82,
    "name": "1001",
    "talle": 100,
    "color": "BLANCO",
    "unit_price": 6354.61,
    "stock": 10,
    "visible": "true",
    "category": "kaury"
  },
  {
    "codigoBarra": "0110100109502",
    "idc": 83,
    "name": "1001",
    "talle": 95,
    "color": "BLANCO",
    "unit_price": 6354.61,
    "stock": 1,
    "visible": "true",
    "category": "kaury"
  },
  {
    "codigoBarra": "0110100109002",
    "idc": 84,
    "name": "1001",
    "talle": 90,
    "color": "BLANCO",
    "unit_price": 6354.61,
    "stock": 5,
    "visible": "true",
    "category": "kaury"
  },
  {
    "codigoBarra": "020813500103",
    "idc": 98,
    "name": "8135",
    "talle": 1,
    "color": "ROJO",
    "unit_price": 6680.11,
    "stock": 8,
    "visible": "true",
    "category": "kaury"
  },
  {
    "codigoBarra": "020813500303",
    "idc": 99,
    "name": "8135",
    "talle": 3,
    "color": "ROJO",
    "unit_price": 6680.11,
    "stock": 0,
    "visible": "true",
    "category": "kaury"
  },
  {
    "codigoBarra": "020023300102",
    "idc": 103,
    "name": "233",
    "talle": 1,
    "color": "NEGRO",
    "unit_price": 5323.5,
    "stock": 4,
    "visible": "true",
    "category": "kaury"
  },
  {
    "codigoBarra": "020023300202",
    "idc": 104,
    "name": "233",
    "talle": 2,
    "color": "NEGRO",
    "unit_price": 5323.5,
    "stock": 1,
    "visible": "true",
    "category": "kaury"
  },
  {
    "codigoBarra": "0200233001100",
    "idc": 105,
    "name": "233",
    "talle": 1,
    "color": "MIEL",
    "unit_price": 5323.5,
    "stock": 1,
    "visible": "true",
    "category": "kaury"
  },
  {
    "codigoBarra": "0200233003100",
    "idc": 106,
    "name": "233",
    "talle": 3,
    "color": "MIEL",
    "unit_price": 5323.5,
    "stock": 4,
    "visible": "true",
    "category": "kaury"
  },
  {
    "codigoBarra": "020023300199",
    "idc": 108,
    "name": "233",
    "talle": 1,
    "color": "NATURAL",
    "unit_price": 5323.5,
    "stock": 0,
    "visible": "true",
    "category": "kaury"
  },
  {
    "codigoBarra": "020023300299",
    "idc": 109,
    "name": "233",
    "talle": 2,
    "color": "NATURAL",
    "unit_price": 5323.5,
    "stock": 0,
    "visible": "true",
    "category": "kaury"
  },
  {
    "codigoBarra": "020023300499",
    "idc": 110,
    "name": "233",
    "talle": 4,
    "color": "NATURAL",
    "unit_price": 5323.5,
    "stock": 1,
    "visible": "true",
    "category": "kaury"
  },
  {
    "codigoBarra": "020810010001",
    "idc": 120,
    "name": "8100",
    "talle": 100,
    "color": "BLANCO",
    "unit_price": 12711.3,
    "stock": 0,
    "visible": "true",
    "category": "kaury"
  },
  {
    "codigoBarra": "02807009058",
    "idc": 121,
    "name": "8070",
    "talle": 90,
    "color": "BORDO",
    "unit_price": 9345.01,
    "stock": 4,
    "visible": "true",
    "category": "kaury"
  },
  {
    "codigoBarra": "02707009078",
    "idc": 122,
    "name": "7070",
    "talle": 90,
    "color": "VERDE C/NUDE",
    "unit_price": 12396.29,
    "stock": 4,
    "visible": "true",
    "category": "kaury"
  },
  {
    "codigoBarra": "020809510090",
    "idc": 123,
    "name": "8095",
    "talle": 100,
    "color": "ROSA VINTAGE",
    "unit_price": 8101.8,
    "stock": 5,
    "visible": "true",
    "category": "kaury"
  },
  {
    "codigoBarra": "020479010001",
    "idc": 128,
    "name": "4790",
    "talle": 100,
    "color": "BLANCO",
    "unit_price": 12721.8,
    "stock": 15,
    "visible": "true",
    "category": "kaury"
  },
  {
    "codigoBarra": "0110100109003",
    "idc": 135,
    "name": "1001",
    "talle": 90,
    "color": "ROJO",
    "unit_price": 6354.61,
    "stock": 0,
    "visible": "true",
    "category": "kaury"
  },
  {
    "codigoBarra": "0110600009503",
    "idc": 136,
    "name": "6000",
    "talle": 95,
    "color": "ROJO",
    "unit_price": 4844.7,
    "stock": 8,
    "visible": "true",
    "category": "kaury"
  },
  {
    "codigoBarra": "020809009091",
    "idc": 141,
    "name": "8090",
    "talle": 90,
    "color": "CELESTE",
    "unit_price": 10248.01,
    "stock": 0,
    "visible": "true",
    "category": "kaury"
  },
  {
    "codigoBarra": "020809010091",
    "idc": 142,
    "name": "8090",
    "talle": 100,
    "color": "CELESTE",
    "unit_price": 10248.01,
    "stock": 3,
    "visible": "true",
    "category": "kaury"
  },
  {
    "codigoBarra": "020810008502",
    "idc": 143,
    "name": "8100",
    "talle": 85,
    "color": "NEGRO",
    "unit_price": 12711.3,
    "stock": 11,
    "visible": "true",
    "category": "kaury"
  },
  {
    "codigoBarra": "020810009002",
    "idc": 144,
    "name": "8100",
    "talle": 90,
    "color": "NEGRO",
    "unit_price": 12711.3,
    "stock": 5,
    "visible": "true",
    "category": "kaury"
  },
  {
    "codigoBarra": "020810009502",
    "idc": 145,
    "name": "8100",
    "talle": 95,
    "color": "NEGRO",
    "unit_price": 12711.3,
    "stock": 0,
    "visible": "true",
    "category": "kaury"
  },
  {
    "codigoBarra": "020810010002",
    "idc": 146,
    "name": "8100",
    "talle": 100,
    "color": "NEGRO",
    "unit_price": 12711.3,
    "stock": 6,
    "visible": "true",
    "category": "kaury"
  },
  {
    "codigoBarra": "100900500000",
    "idc": 124,
    "name": "P15",
    "unit_price": 8074.51,
    "stock": 40,
    "visible": "true",
    "category": "kaury"
  },
  {
    "codigoBarra": "100001600000",
    "idc": 125,
    "name": "P16",
    "unit_price": 9529.79,
    "stock": 103,
    "visible": "true",
    "category": "kaury"
  },
  {
    "codigoBarra": "100001800012",
    "idc": 126,
    "name": "P18",
    "unit_price": 8557.5,
    "stock": -5,
    "visible": "true",
    "category": "kaury"
  },
  {
    "codigoBarra": "100003500012",
    "idc": 1,
    "name": "P35",
    "unit_price": 6902.7,
    "stock": 2,
    "visible": "true",
    "category": "kaury"
  },
  {
    "codigoBarra": "100003400012",
    "idc": 2,
    "name": "P34",
    "unit_price": 5758.21,
    "stock": 1,
    "visible": "true",
    "category": "kaury"
  },
  {
    "codigoBarra": "100006600003",
    "idc": 4,
    "name": "P66",
    "unit_price": 6153.01,
    "stock": 22,
    "visible": "true",
    "category": "kaury"
  }
]
